setup.py
zfx_dir/__init__.py
zfx_dir/创建目录.py
zfx_dir/删除目录.py
zfx_dir/取子目录数量.py
zfx_dir/取目录大小.py
zfx_dir/取系统桌面目录.py
zfx_dir/取运行目录.py
zfx_dir.egg-info/PKG-INFO
zfx_dir.egg-info/SOURCES.txt
zfx_dir.egg-info/dependency_links.txt
zfx_dir.egg-info/top_level.txt